setup.cfg
setup.py
function_logger/__init__.py
function_logger.egg-info/PKG-INFO
function_logger.egg-info/SOURCES.txt
function_logger.egg-info/dependency_links.txt
function_logger.egg-info/top_level.txt
function_logger.egg-info/zip-safe