Metadata-Version: 1.0
Name: function-logger
Version: 0.1
Summary: logs the function functionality
Home-page: https://github.com/anandtripathi5/function_logger
Author: Anand Tripathi
Author-email: anand.tripathi507@gmail.com
License: UNKNOWN
Platform: UNKNOWN
